hilbert_cli.py
elemem_sdk/__init__.py
elemem_sdk/client_demo.py
elemem_sdk/hilbert_client.py
elemem_sdk/rmi_client.py
elemem_sdk/rmi_http_demo.py
elemem_sdk/rmi_pb2.py
elemem_sdk/rmi_pb2_grpc.py
elemem_sdk/sdk_pb2.py
elemem_sdk/sdk_pb2_grpc.py
elemem_sdk/server.py
elemem_sdk/setup.py
elemem_sdk/proto/__init__.py
elemem_sdk/proto/sdk_pb2.py
elemem_sdk/proto/sdk_pb2_grpc.py
elemem_vector_sdk-2.1.0.2.dist-info/METADATA
elemem_vector_sdk-2.1.0.2.dist-info/WHEEL
elemem_vector_sdk-2.1.0.2.dist-info/entry_points.txt
elemem_vector_sdk-2.1.0.2.dist-info/top_level.txt
elemem_vector_sdk-2.1.0.2.dist-info/RECORD
