Metadata-Version: 2.4
Name: elemem_vector_sdk
Version: 2.1.0.2
Summary: A Python SDK for elem
Author: elemem.tech
Author-email: support@elemem.tech
Classifier: Programming Language :: Python :: 3
Classifier: License :: OSI Approved :: MIT License
Classifier: Operating System :: OS Independent
Requires-Python: >=3.6
Requires-Dist: grpcio==1.74.0
Requires-Dist: grpcio-tools==1.74.0
Requires-Dist: numpy==1.26.4
Requires-Dist: tqdm==4.67.1
Requires-Dist: h5py==3.14.0
Requires-Dist: protobuf==6.31.1
Dynamic: author
Dynamic: author-email
Dynamic: classifier
Dynamic: description
Dynamic: description-content-type
Dynamic: requires-dist
Dynamic: requires-python
Dynamic: summary
